fair_trees/__init__.py
fair_trees/datasets.pkl
fair_trees/fair_trees.py
fair_trees-2.6.6.dist-info/licenses/LICENSE
fair_trees-2.6.6.dist-info/METADATA
fair_trees-2.6.6.dist-info/WHEEL
fair_trees-2.6.6.dist-info/top_level.txt
fair_trees-2.6.6.dist-info/RECORD
