Metadata-Version: 2.4
Name: fair_trees
Version: 2.6.6
Summary: This package learns fair decision tree classifiers which can then be bagged into fair random forests, following the scikit-learn API standards.
Home-page: https://github.com/pereirabarataap/fair_tree_classifier
Author: Antonio Pereira Barata
Author-email: apbarata@gmail.com
License: MIT
Classifier: Programming Language :: Python :: 3
Classifier: License :: OSI Approved :: MIT License
Classifier: Operating System :: OS Independent
Classifier: Intended Audience :: Developers
Classifier: Intended Audience :: Science/Research
Classifier: Topic :: Scientific/Engineering :: Artificial Intelligence
Requires-Python: >=3.6
License-File: LICENSE
Requires-Dist: scipy
Requires-Dist: numpy
Requires-Dist: pandas
Requires-Dist: joblib
Requires-Dist: scikit-learn
Requires-Dist: importlib-resources; python_version < "3.9"
Dynamic: license-file
